README
setup.py
cmsplugin_nextlink/__init__.py
cmsplugin_nextlink/admin.py
cmsplugin_nextlink/cms_plugins.py
cmsplugin_nextlink/forms.py
cmsplugin_nextlink/models.py
cmsplugin_nextlink/utils.py
cmsplugin_nextlink/validator.py
cmsplugin_nextlink.egg-info/PKG-INFO
cmsplugin_nextlink.egg-info/SOURCES.txt
cmsplugin_nextlink.egg-info/dependency_links.txt
cmsplugin_nextlink.egg-info/requires.txt
cmsplugin_nextlink.egg-info/top_level.txt
cmsplugin_nextlink/migrations/0001_initial.py
cmsplugin_nextlink/migrations/0002_auto__add_field_nextlink_image__add_field_nextlink_alt_attribute.py
cmsplugin_nextlink/migrations/0003_auto__add_field_nextlink_description.py
cmsplugin_nextlink/migrations/0004_auto__del_field_nextlink_link_create__add_field_nextlink_link_created.py
cmsplugin_nextlink/migrations/0005_auto__del_field_nextlink_access_key__del_field_nextlink_title__del_fie.py
cmsplugin_nextlink/migrations/__init__.py