Metadata-Version: 1.1
Name: cmsplugin-nextlink
Version: 0.0.2.1
Summary: This is a link plugin for django-cms 2.2
Home-page: http://bitbucket.org/igraltist/cmsplugin-nextlink
Author: Jens Kasten
Author-email: jens@kasten-edv.de
License: GPL3
Download-URL: http://bitbucket.org/igraltist/cmsplugin-nextlink
Platform: UNKNOWN
Classifier: Development Status :: 4 - Beta
Classifier: Environment :: Web Environment
Classifier: Intended Audience :: Developers
Classifier: License :: OSI Approved :: GNU General Public License v3 (GPLv3)
Classifier: Operating System :: OS Independent
Classifier: Programming Language :: Python
Classifier: Framework :: Django
